ifcalendar/__init__.py
ifcalendar/ifc.py
ifcalendar-0.1.3.dist-info/LICENSE
ifcalendar-0.1.3.dist-info/METADATA
ifcalendar-0.1.3.dist-info/WHEEL
ifcalendar-0.1.3.dist-info/top_level.txt
ifcalendar-0.1.3.dist-info/RECORD
