Metadata-Version: 2.1
Name: ifcalendar
Version: 0.1.3
Summary: Cotsworth Calendar or International Fixed Calendar for Statistical Analysis and Experiments
Home-page: https://github.com/msampathkumar/ifcalendar
Author: Sampath Maddula
Author-email: sam1990kumar@gmail.com
License: UNKNOWN
Platform: UNKNOWN
